Metadata-Version: 1.1
Name: TwitterScraperAPI
Version: 1.0.16
Summary: Library for getting twitter data
Home-page: https://github.com/vaskrneup/TwitterScraperAPI
Author: Bhaskar Neupane
Author-email: bhaskar.neupane.58@gmail.com
License: MIT
Keywords: twitter scraper
Platform: UNKNOWN
Classifier: Development Status :: 4 - Beta
Classifier: Intended Audience :: Developers
Classifier: Operating System :: OS Independent
Classifier: License :: OSI Approved :: MIT License
Classifier: Programming Language :: Python :: 3
